README.md
setup.py
sweet.dubbo.egg-info/PKG-INFO
sweet.dubbo.egg-info/SOURCES.txt
sweet.dubbo.egg-info/dependency_links.txt
sweet.dubbo.egg-info/requires.txt
sweet.dubbo.egg-info/top_level.txt
sweet/modules/dubbo.py